cms_general_algorithm/__init__.py
cms_general_algorithm/common.py
cms_general_algorithm/data_utils.py
cms_general_algorithm/frequncy.py
cms_general_algorithm/paint.py
cms_general_algorithm-1.0.1.dist-info/METADATA
cms_general_algorithm-1.0.1.dist-info/WHEEL
cms_general_algorithm-1.0.1.dist-info/top_level.txt
cms_general_algorithm-1.0.1.dist-info/RECORD
