Metadata-Version: 2.1
Name: cms-general-algorithm
Version: 1.0.1
Summary: sany cms general algorithm sets
Author: liuh300
Author-email: liuh300@sany.com.cn
Keywords: cms algorithm
Platform: all
Classifier: Intended Audience :: Developers
Classifier: Operating System :: OS Independent
Classifier: Natural Language :: Chinese (Simplified)
Classifier: Programming Language :: Python
Classifier: Programming Language :: Python :: 2
Classifier: Programming Language :: Python :: 2.7
Classifier: Programming Language :: Python :: 3
Classifier: Programming Language :: Python :: 3.5
Classifier: Programming Language :: Python :: 3.6
Classifier: Programming Language :: Python :: 3.7
Classifier: Programming Language :: Python :: 3.8
Classifier: Topic :: Software Development :: Libraries
Requires-Dist: sqlalchemy
Requires-Dist: requests
Requires-Dist: pandas
Requires-Dist: sanydata
Requires-Dist: matplotlib
Requires-Dist: scipy
